CHANGES.rst
CONTRIBUTORS.rst
LICENSE
MANIFEST.in
README.rst
buildout.cfg
setup.py
travis.cfg
docs/LICENSE.GPL
docs/LICENSE.rst
src/collective/__init__.py
src/collective.js.tablednd.egg-info/PKG-INFO
src/collective.js.tablednd.egg-info/SOURCES.txt
src/collective.js.tablednd.egg-info/dependency_links.txt
src/collective.js.tablednd.egg-info/entry_points.txt
src/collective.js.tablednd.egg-info/namespace_packages.txt
src/collective.js.tablednd.egg-info/not-zip-safe
src/collective.js.tablednd.egg-info/requires.txt
src/collective.js.tablednd.egg-info/top_level.txt
src/collective/js/__init__.py
src/collective/js/tablednd/__init__.py
src/collective/js/tablednd/configure.zcml
src/collective/js/tablednd/interfaces.py
src/collective/js/tablednd/setuphandlers.py
src/collective/js/tablednd/testing.py
src/collective/js/tablednd/testing.zcml
src/collective/js/tablednd/browser/__init__.py
src/collective/js/tablednd/browser/configure.zcml
src/collective/js/tablednd/browser/overrides/.gitkeep
src/collective/js/tablednd/browser/static/.gitkeep
src/collective/js/tablednd/browser/static/jquery.tablednd.js
src/collective/js/tablednd/profiles/default/browserlayer.xml
src/collective/js/tablednd/profiles/default/collectivejstablednd_marker.txt
src/collective/js/tablednd/profiles/default/jsregistry.xml
src/collective/js/tablednd/profiles/default/metadata.xml
src/collective/js/tablednd/profiles/testing/collectivejstablednd_testing.txt
src/collective/js/tablednd/profiles/testing/metadata.xml
src/collective/js/tablednd/tests/__init__.py
src/collective/js/tablednd/tests/test_robot.py
src/collective/js/tablednd/tests/test_setup.py
src/collective/js/tablednd/tests/robot/test_example.robot