Metadata-Version: 2.1
Name: collective.js.tablednd
Version: 0.1
Summary: Plone integration of TableDND jquery plugin
Home-page: http://pypi.python.org/pypi/collective.js.tablednd
Author: Gauthier BASTIEN
Author-email: gauthier.bastien@imio.be
License: GPL
Keywords: Python Plone
Platform: UNKNOWN
Classifier: Environment :: Web Environment
Classifier: Framework :: Plone
Classifier: Framework :: Plone :: 4.3
Classifier: Programming Language :: Python
Classifier: Programming Language :: Python :: 2.7
Provides-Extra: test
